ormantism/__init__.py
ormantism/connection.py
ormantism/field.py
ormantism/join_info.py
ormantism/table.py
ormantism/transaction.py
ormantism/utils/__init__.py
ormantism/utils/find_subclass.py
ormantism/utils/get_base_type.py
ormantism/utils/get_table_by_name.py
ormantism/utils/is_type_annotation.py
ormantism/utils/make_hashable.py
ormantism/utils/rebuild_pydantic_model.py
ormantism/utils/resolve_type.py
ormantism/utils/serialize.py
ormantism/utils/supermodel.py
ormantism-0.5.8.dist-info/licenses/LICENCE
ormantism-0.5.8.dist-info/METADATA
ormantism-0.5.8.dist-info/WHEEL
ormantism-0.5.8.dist-info/top_level.txt
ormantism-0.5.8.dist-info/RECORD
