Metadata-Version: 2.4
Name: ormantism
Version: 0.5.8
Summary: A lightweight ORM built on Pydantic for simple CRUD operations with minimal code
Author: Mathieu Rodic
License: MIT
Project-URL: Homepage, https://github.com/mathieurodic/ormantism
Keywords: orm,pydantic,sqlite,SQLite,MySQL,PostgreSQL
Classifier: License :: OSI Approved :: MIT License
Requires-Python: >=3.12
License-File: LICENCE
Requires-Dist: pydantic>=2.11.7
Requires-Dist: pydantic_core>=2.33.2
Requires-Dist: datamodel_code_generator>=0.31.2
Dynamic: license-file
